{
  "to_pricing": "Heading to Pricing. I'll highlight what actually matters.",
  "to_builder": "Opening GOAT Builder — the fun part.",
  "to_vault": "Vault access granted. Don't lose anything you want to keep.",
  "back_home": "Returning to Dashboard. Fresh start, clear head.",
  "to_drafts": "Opening Draft Engine. Let's create something powerful.",
  "to_settings": "Settings panel. Customize your workflow.",
  "to_help": "Help system activated. What do you need?",
  "to_projects": "Your projects. Pick one or start fresh.",
  "menu_open": "Navigation ready. Where to next?",
  "menu_close": "Back to work. Focus restored."
}