{
  "order_id": "booklet_a8612926773b",
  "user_id": "demo_user_123",
  "created_at": "2026-01-06T19:12:48.156202",
  "status": "draft",
  "content_file": {
    "filename": "training_manual.pdf",
    "size": 5242880,
    "uploaded_at": "2026-01-06T19:12:48.156202",
    "status": "uploaded"
  },
  "cart": {
    "items": [
      {
        "pass_id": "foundation",
        "name": "Foundation Pass",
        "description": "Parse & Organize - Core structure and correctness. Includes: logical flow, section hierarchy, proper pagination, margins, center-fold safety, print-safe export.",
        "price": 3488,
        "selected": true,
        "required": true
      }
    ],
    "subtotal": 3488,
    "tax": 0,
    "total": 3488
  },
  "payment_status": "not_started",
  "payment_intent_id": null,
  "processing_status": "not_started",
  "outputs": {},
  "metadata": {
    "estimated_pages": 125,
    "estimated_sheets": 31.25
  },
  "last_updated": "2026-01-06T19:12:48.159202"
}